{
  "collectionName": "components_elements_feature_rows",
  "info": {
    "displayName": "Feature row",
    "description": ""
  },
  "options": {},
  "attributes": {
    "title": {
      "type": "string",
      "required": true
    },
    "description": {
      "type": "text"
    },
    "media": {
      "type": "media",
      "multiple": false,
      "required": true,
      "allowedTypes": [
        "images",
        "videos"
      ]
    },
    "link": {
      "type": "component",
      "repeatable": false,
      "component": "links.link"
    }
  }
}
